[
    {
        "id": 1 ,
        "name": "الاسلامية" ,
        "img":  "https://ka6rar.github.io/DtatBook/stage_1_class_4_img/كتاب الاسلامية الرابع الابتدائي_page-0001.jpg" ,
        "file": "https://bk1.shr4.com/books/b4/2023-2024/%d9%83%d8%aa%d8%a7%d8%a8%20%d8%a7%d9%84%d8%a7%d8%b3%d9%84%d8%a7%d9%85%d9%8a%d8%a9%20%d8%a7%d9%84%d8%b1%d8%a7%d8%a8%d8%b9%20%d8%a7%d9%84%d8%a7%d8%a8%d8%aa%d8%af%d8%a7%d8%a6%d9%8a.pdf" 
    }
    ,
    {
        "id": 2 ,
        "name": "القراءة" ,
        "img":  "https://ka6rar.github.io/DtatBook/stage_1_class_4_img/كتاب القراءة الرابع الابتدائي_page-0001.jpg" ,
        "file": "https://bk1.shr4.com/books/b4/2023-2024/%d9%83%d8%aa%d8%a7%d8%a8%20%d8%a7%d9%84%d9%82%d8%b1%d8%a7%d8%a1%d8%a9%20%d8%a7%d9%84%d8%b1%d8%a7%d8%a8%d8%b9%20%d8%a7%d9%84%d8%a7%d8%a8%d8%aa%d8%af%d8%a7%d8%a6%d9%8a.pdf" 
    }
    ,   {
        "id": 3 ,
        "name": "القواعد" ,
        "img":  "https://ka6rar.github.io/DtatBook/stage_1_class_4_img/كتاب القواعد الرابع الابتدائي_page-0001.jpg" ,
        "file": "https://bk1.shr4.com/books/b4/2023-2024/%d9%83%d8%aa%d8%a7%d8%a8%20%d8%a7%d9%84%d9%82%d9%88%d8%a7%d8%b9%d8%af%20%d8%a7%d9%84%d8%b1%d8%a7%d8%a8%d8%b9%20%d8%a7%d9%84%d8%a7%d8%a8%d8%aa%d8%af%d8%a7%d8%a6%d9%8a.pdf" 
    }
    ,   {
        "id": 4 ,
        "name": "الانكليزي الطالب" ,
        "img":  "https://ka6rar.github.io/DtatBook/stage_1_class_4_img/كتاب الانكليزي الطالب الرابع ابتدائي_page-0001.jpg" ,
        "file": "https://bk1.shr4.com/books/b4/2023-2024/%d9%85%d8%b7%d8%a7%d8%a8%d9%82/%d9%83%d8%aa%d8%a7%d8%a8%20%d8%a7%d9%84%d8%a7%d9%86%d9%83%d9%84%d9%8a%d8%b2%d9%8a%20%d8%a7%d9%84%d8%b7%d8%a7%d9%84%d8%a8%20%d8%a7%d9%84%d8%b1%d8%a7%d8%a8%d8%b9%20%d8%a7%d8%a8%d8%aa%d8%af%d8%a7%d8%a6%d9%8a.pdf" 
    }
    ,   {
        "id": 5 ,
        "name": "الانكليزي النشاط" ,
        "img":  "https://ka6rar.github.io/DtatBook/stage_1_class_4_img/كتاب الانكليزي النشاط الرابع ابتدائي_page-0001.jpg" ,
        "file": "https://bk1.shr4.com/books/b4/2023-2024/%d9%85%d8%b7%d8%a7%d8%a8%d9%82/%d9%83%d8%aa%d8%a7%d8%a8%20%d8%a7%d9%84%d8%a7%d9%86%d9%83%d9%84%d9%8a%d8%b2%d9%8a%20%d8%a7%d9%84%d9%86%d8%b4%d8%a7%d8%b7%20%d8%a7%d9%84%d8%b1%d8%a7%d8%a8%d8%b9%20%d8%a7%d8%a8%d8%aa%d8%af%d8%a7%d8%a6%d9%8a.pdf" 
    }
    ,   {
        "id":  6,
        "name": " الرياضيات الملون" ,
        "img":  "https://ka6rar.github.io/DtatBook/stage_1_class_4_img/كتاب الرياضيات الرابع الابتدائي_page-0001.jpg" ,
        "file": "https://bk1.shr4.com/books/b4/2023-2024/%d9%83%d8%aa%d8%a7%d8%a8%20%d8%a7%d9%84%d8%b1%d9%8a%d8%a7%d8%b6%d9%8a%d8%a7%d8%aa%20%d8%a7%d9%84%d8%b1%d8%a7%d8%a8%d8%b9%20%d8%a7%d9%84%d8%a7%d8%a8%d8%aa%d8%af%d8%a7%d8%a6%d9%8a.pdf" 
    }
    ,   {
        "id": 7 ,
        "name": "الرياضيات التمرينات" ,
        "img":  "https://ka6rar.github.io/DtatBook/stage_1_class_4_img/كتاب الرياضيات التمرينات الرابع الابتدائي_page-0001.jpg" ,
        "file": "https://bk1.shr4.com/books/b4/2023-2024/%d9%83%d8%aa%d8%a7%d8%a8%20%d8%a7%d9%84%d8%b1%d9%8a%d8%a7%d8%b6%d9%8a%d8%a7%d8%aa%20%d8%a7%d9%84%d8%aa%d9%85%d8%b1%d9%8a%d9%86%d8%a7%d8%aa%20%d8%a7%d9%84%d8%b1%d8%a7%d8%a8%d8%b9%20%d8%a7%d9%84%d8%a7%d8%a8%d8%aa%d8%af%d8%a7%d8%a6%d9%8a.pdf" 
    }
    ,   {
        "id": 8 ,
        "name": "العلوم الملون" ,
        "img":  "https://ka6rar.github.io/DtatBook/stage_1_class_4_img/مقدمة ومهارات.indd_page-0001.jpg" ,
        "file": "https://bk1.shr4.com/books/b4/2023-2024/%d9%83%d8%aa%d8%a7%d8%a8%20%d8%a7%d9%84%d8%b9%d9%84%d9%88%d9%85%20%d8%a7%d9%84%d8%b1%d8%a7%d8%a8%d8%b9%20%d8%a7%d9%84%d8%a7%d8%a8%d8%aa%d8%af%d8%a7%d8%a6%d9%8a.pdf" 
    }
    ,   {
        "id": 9 ,
        "name": " العلوم النشاط " ,
        "img":  "https://ka6rar.github.io/DtatBook/stage_1_class_4_img/كتاب العلوم النشاط الرابع الابتدائي_page-0001.jpg" ,
        "file": "https://bk1.shr4.com/books/b4/2023-2024/%d9%83%d8%aa%d8%a7%d8%a8%20%d8%a7%d9%84%d8%b9%d9%84%d9%88%d9%85%20%d8%a7%d9%84%d9%86%d8%b4%d8%a7%d8%b7%20%d8%a7%d9%84%d8%b1%d8%a7%d8%a8%d8%b9%20%d8%a7%d9%84%d8%a7%d8%a8%d8%aa%d8%af%d8%a7%d8%a6%d9%8a.pdf" 
    }
    ,   {
        "id": 9 ,
        "name": "الاجتماعيات" ,
        "img":  "https://ka6rar.github.io/DtatBook/stage_1_class_4_img/كتاب الاجتماعيات الرابع الابتدائي_page-0001.jpg" ,
        "file": "https://bk1.shr4.com/books/b4/2023-2024/%d9%83%d8%aa%d8%a7%d8%a8%20%d8%a7%d9%84%d8%a7%d8%ac%d8%aa%d9%85%d8%a7%d8%b9%d9%8a%d8%a7%d8%aa%20%d8%a7%d9%84%d8%b1%d8%a7%d8%a8%d8%b9%20%d8%a7%d9%84%d8%a7%d8%a8%d8%aa%d8%af%d8%a7%d8%a6%d9%8a.pdf" 
    }
]